tatools/ParamsBase.py
tatools/__init__.py
tatools/About/AI_about.py
tatools/About/License.py
tatools/About/License_Check.py
tatools/About/__init__.py
tatools/IVIS_Data/__init__.py
tatools/Thoi_gian/__init__.py
tatools/Thoi_gian/taTimers.py
tatools/file_folder/__init__.py
tatools/file_folder/delete_files_in_directory.py
tatools-0.2.dist-info/LICENSE
tatools-0.2.dist-info/METADATA
tatools-0.2.dist-info/WHEEL
tatools-0.2.dist-info/entry_points.txt
tatools-0.2.dist-info/top_level.txt
tatools-0.2.dist-info/RECORD
