Metadata-Version: 2.1
Name: tatools
Version: 0.2
Summary: Thư viện hữu ích của Tuấn Anh.
Home-page: https://pypi.org/project/tatools/
Author: Tuấn Anh - Foxconn
Author-email: nt.anh.fai@gmail.com
License: MIT
Classifier: Programming Language :: Python :: 3
Classifier: License :: OSI Approved :: MIT License
Classifier: Operating System :: OS Independent
License-File: LICENSE
Requires-Dist: ruamel.yaml
Requires-Dist: lxml
Requires-Dist: tqdm
